dockerinfo/__init__.py
dockerinfo/dockerinfo.py
dockerinfo-1.4.3.dist-info/LICENSE
dockerinfo-1.4.3.dist-info/METADATA
dockerinfo-1.4.3.dist-info/WHEEL
dockerinfo-1.4.3.dist-info/top_level.txt
dockerinfo-1.4.3.dist-info/RECORD
