Metadata-Version: 2.1
Name: dockerinfo
Version: 1.4.3
Summary: Dockerinfo - Easily extract information from docker containers
Home-page: https://github.com/croketillo/dockerinfo
Author: croketillo
Author-email: croketillo@gmail.com
License: GNU GENERAL PUBLIC LICENSE
Keywords: docker,dockerinfo,docker module,docker info
Classifier: Intended Audience :: Developers
Classifier: Topic :: Software Development :: Build Tools
Classifier: Programming Language :: Python :: 2.7
Classifier: Programming Language :: Python :: 3.4
Classifier: Programming Language :: Python :: 3.5
Classifier: Programming Language :: Python :: 3.6
Classifier: Programming Language :: Python :: 3.7
Classifier: Topic :: System :: Systems Administration
Classifier: Topic :: Utilities
License-File: LICENSE
Requires-Dist: docker
